[
  {
    "time": 86636,
    "lyric": "编曲 Arranger：陈永辉Yonghui.C(HOYO-MiX)",
    "translation": "",
    "romaji": ""
  },
  {
    "time": 87636,
    "lyric": "演唱Vocal Artist：王可鑫Eli.W(HOYO-MiX)",
    "translation": "",
    "romaji": ""
  },
  {
    "time": 88636,
    "lyric": "混音 Mixing Engineer：陈永辉Yonghui.C(HOYO-MiX)",
    "translation": "",
    "romaji": ""
  },
  {
    "time": 89636,
    "lyric": "母带 Mastering Engineer：李敬浩Hao(HOYO-MiX)",
    "translation": "",
    "romaji": ""
  },
  {
    "time": 90636,
    "lyric": "出品 Produced by：HOYO-MiX",
    "translation": "",
    "romaji": ""
  }
]