[
  {
    "time": 0,
    "lyric": "作曲 : 苑迪萌 Dimeng Yuan (HOYO-MiX)",
    "translation": "",
    "romaji": ""
  },
  {
    "time": 55,
    "lyric": "编曲 : 陈子敏 Arcangelo Chen (HOYO-MiX)",
    "translation": "",
    "romaji": ""
  },
  {
    "time": 1011,
    "lyric": "制作人 : HOYO-MiX",
    "translation": "",
    "romaji": ""
  },
  {
    "time": 1066,
    "lyric": "乐队 Orchestra：Budapest Scoring Orchestra / 龙之艺交响乐团 Art of Loong Orchestra",
    "translation": "",
    "romaji": ""
  },
  {
    "time": 2022,
    "lyric": "录音棚 Recording Studio：Budapest Scoring / 上海广播大厦 Shanghai Media Group",
    "translation": "",
    "romaji": ""
  },
  {
    "time": 2077,
    "lyric": "录音师 Recording Engineer：Viktor Szabó / 莫家伟 Jiawei Mo",
    "translation": "",
    "romaji": ""
  },
  {
    "time": 3033,
    "lyric": "混音师 Mixing Engineer：李海 Hai Li / 罗筱薇 Sabrina Luo",
    "translation": "",
    "romaji": ""
  },
  {
    "time": 3088,
    "lyric": "母带制作 Mastering Engineer：黄巍 Zach Huang",
    "translation": "",
    "romaji": ""
  },
  {
    "time": 4044,
    "lyric": "出品 Produced by：HOYO-MiX",
    "translation": "",
    "romaji": ""
  },
  {
    "time": 5000,
    "lyric": "纯音乐，请欣赏",
    "translation": "",
    "romaji": ""
  }
]