[
  {
    "time": 0,
    "lyric": "作词 : 哈尼 Hani/项柳 Hsiang Liu",
    "translation": "",
    "romaji": ""
  },
  {
    "time": 1000,
    "lyric": "作曲 : 苑迪萌 Dimeng Yuan (HOYO-MiX)",
    "translation": "",
    "romaji": ""
  },
  {
    "time": 2000,
    "lyric": "编曲 : 索德尔 Deer Suo (HOYO-MiX)/尤裴佳 Peijia You (HOYO-MiX)",
    "translation": "",
    "romaji": ""
  },
  {
    "time": 3000,
    "lyric": "制作人 : HOYO-MiX",
    "translation": "",
    "romaji": ""
  },
  {
    "time": 4000,
    "lyric": "制谱 Music Copyist：索德尔 Deer Suo (HOYO-MiX)",
    "translation": "",
    "romaji": ""
  },
  {
    "time": 5000,
    "lyric": "斯瓦希里语顾问 Swahili Language Consultant：Sarah Mirza",
    "translation": "",
    "romaji": ""
  },
  {
    "time": 6000,
    "lyric": "乐队 Orchestra：Budapest Scoring Orchestra / 国际首席爱乐乐团 International Master Philharmonic Orchestra",
    "translation": "",
    "romaji": ""
  },
  {
    "time": 7000,
    "lyric": "电吉他 Electric Guitar：尤裴佳 Peijia You (HOYO-MiX)",
    "translation": "",
    "romaji": ""
  },
  {
    "time": 8000,
    "lyric": "合唱 Choir：Budapest Scoring Choir",
    "translation": "",
    "romaji": ""
  },
  {
    "time": 9000,
    "lyric": "录音棚 Recording Studio：Budapest Scoring / 九紫天诚录音棚 SKY FIRE STUDIO",
    "translation": "",
    "romaji": ""
  },
  {
    "time": 10000,
    "lyric": "录音师 Recording Engineer：Viktor Szabó / 董方昱 Fangyu Dong",
    "translation": "",
    "romaji": ""
  },
  {
    "time": 11000,
    "lyric": "混音师 Mixing Engineer：鸦雀有声 Anzol",
    "translation": "",
    "romaji": ""
  },
  {
    "time": 12000,
    "lyric": "母带制作 Mastering Engineer：鸦雀有声 Anzol",
    "translation": "",
    "romaji": ""
  },
  {
    "time": 13000,
    "lyric": "出品 Produced by：HOYO-MiX",
    "translation": "",
    "romaji": ""
  },
  {
    "time": 41015,
    "lyric": "Shambulia! Beba silaha / 出征，肩负一切",
    "translation": "",
    "romaji": ""
  },
  {
    "time": 47044,
    "lyric": "Pigana mpaka mwishowe / 战斗，直至终结",
    "translation": "",
    "romaji": ""
  },
  {
    "time": 54048,
    "lyric": "Kwa nchi yetu tutaunguza damu yoyote / 为了家园燃尽最后的血",
    "translation": "",
    "romaji": ""
  },
  {
    "time": 60091,
    "lyric": "Rudi kwa pambaja ya dunia / 回归大地下的深壑",
    "translation": "",
    "romaji": ""
  },
  {
    "time": 66038,
    "lyric": "Zuri, safi, sawa, sikia",
    "translation": "",
    "romaji": ""
  },
  {
    "time": 72073,
    "lyric": "Vuma, raha, nguvu, sikia",
    "translation": "",
    "romaji": ""
  },
  {
    "time": 82052,
    "lyric": "Hadithi yaendelea (kama moto) / 故事仍在延续，正如烈火",
    "translation": "",
    "romaji": ""
  },
  {
    "time": 88088,
    "lyric": "Heshima warithi vizazi (waka daima) / 荣耀几经传承，永燃不息",
    "translation": "",
    "romaji": ""
  },
  {
    "time": 92046,
    "lyric": "Ushujaa waangaza mbingu na ardhi / 勇气点亮天空与大地",
    "translation": "",
    "romaji": ""
  },
  {
    "time": 98078,
    "lyric": "Mara tena ashinda Natlan / 纳塔再一次迎来胜利",
    "translation": "",
    "romaji": ""
  },
  {
    "time": 123027,
    "lyric": "Nyimbo kelele sana / 听吧，歌声渐响",
    "translation": "",
    "romaji": ""
  },
  {
    "time": 135092,
    "lyric": "Kwa jamaa, nchi na taifa (Zuri, safi, sawa) / 为家人，为故乡，为国家（为了荣光）",
    "translation": "",
    "romaji": ""
  },
  {
    "time": 148060,
    "lyric": "Kwa matumaini, mbeleni, malengo (Vuma, raha, nguvu) / 为理想，为愿望，为未来（为了希望）",
    "translation": "",
    "romaji": ""
  },
  {
    "time": 173081,
    "lyric": "Mara ya tena mwangani / 再一次，再一次，燃烧",
    "translation": "",
    "romaji": ""
  },
  {
    "time": 186044,
    "lyric": "Mara ya tena mwangani / 再一次，再一次，燃烧",
    "translation": "",
    "romaji": ""
  },
  {
    "time": 199004,
    "lyric": "Maisha marefu ni sasa / 这就是新生的时刻",
    "translation": "",
    "romaji": ""
  },
  {
    "time": 205038,
    "lyric": "Maisha marefu ni sasa / 这就是新生的时刻",
    "translation": "",
    "romaji": ""
  },
  {
    "time": 211070,
    "lyric": "Maisha marefu ni sasa / 这就是新生的时刻",
    "translation": "",
    "romaji": ""
  },
  {
    "time": 217098,
    "lyric": "Maisha marefu ni sasa / 这就是新生的时刻",
    "translation": "",
    "romaji": ""
  }
]