[
  {
    "time": 0,
    "lyric": "作词 : 夏轶瀚Sya",
    "translation": "",
    "romaji": ""
  },
  {
    "time": 545,
    "lyric": "作曲 : 蔡近翰Zoe(HOYO-MiX)",
    "translation": "",
    "romaji": ""
  },
  {
    "time": 630,
    "lyric": "",
    "translation": "",
    "romaji": "Arrangement:te i u ka i JODODO"
  },
  {
    "time": 1090,
    "lyric": "编曲 : 郑宇界JODODO(HOYO-MiX)",
    "translation": "",
    "romaji": ""
  },
  {
    "time": 1630,
    "lyric": "",
    "translation": "",
    "romaji": "Producer:sa i ki n ka n Zoe"
  },
  {
    "time": 1635,
    "lyric": "制作人 : 蔡近翰Zoe(HOYO-MiX)",
    "translation": "",
    "romaji": ""
  },
  {
    "time": 2180,
    "lyric": "千本の刃 奏でる",
    "translation": "万千刀剑交响奏鸣",
    "romaji": "se n bo n no ha ka na de ru"
  },
  {
    "time": 7930,
    "lyric": "彼岸の夜風",
    "translation": "彼岸夜风",
    "romaji": "hi ga n no yo ru ka ze"
  },
  {
    "time": 13470,
    "lyric": "黒風が吹き抜ける",
    "translation": "狂风肆虐",
    "romaji": "ku ro ka ze ga fu ki nu ke ru"
  },
  {
    "time": 19270,
    "lyric": "宮殿の片隅",
    "translation": "掠过宫殿一隅",
    "romaji": "kyu u de n no ka ta su mi"
  },
  {
    "time": 25210,
    "lyric": "無常の風",
    "translation": "无常之风",
    "romaji": "mu jo u no ka ze"
  },
  {
    "time": 30770,
    "lyric": "千年の羽",
    "translation": "千年之羽",
    "romaji": "se n ne n no ha ne"
  },
  {
    "time": 36400,
    "lyric": "儚い祈りが",
    "translation": "渺无望之祈愿",
    "romaji": "ha ka na i i no ri ga"
  },
  {
    "time": 39030,
    "lyric": "囚われの翼",
    "translation": "乃受囚之翼",
    "romaji": "to ra wa re no tsu ba sa"
  },
  {
    "time": 42030,
    "lyric": "彷徨うより時を越えて",
    "translation": "彷徨间早已时光飞逝",
    "romaji": "ho u ko u u yo ri to ki wo ko e"
  },
  {
    "time": 47890,
    "lyric": "虹色の羽が",
    "translation": "七色彩羽",
    "romaji": "ni ji i ro no ha ne ga"
  },
  {
    "time": 50560,
    "lyric": "血塗りの道で天火を浴びよ",
    "translation": "于血染之道身负天火",
    "romaji": "chi nu ri no mi chi de te n ka wo a bi yo"
  },
  {
    "time": 75500,
    "lyric": "千本の椿 唱える",
    "translation": "万千大椿低声咏唱",
    "romaji": "se n bo n no tsu ba ki to na e ru"
  },
  {
    "time": 81170,
    "lyric": "悲願の夜雨",
    "translation": "悲愿夜雨",
    "romaji": "hi ga n no yo sa me"
  },
  {
    "time": 86830,
    "lyric": "非情な雨 濡れた人",
    "translation": "为无情之雨湿身者",
    "romaji": "hi jo u na a me nu re ta hi to"
  },
  {
    "time": 92580,
    "lyric": "宮殿の片隅",
    "translation": "立于宫殿一隅",
    "romaji": "kyu u de n no ka ta su mi de"
  },
  {
    "time": 98260,
    "lyric": "無明の淵",
    "translation": "无明之渊",
    "romaji": "mu myo u no fu chi"
  },
  {
    "time": 104090,
    "lyric": "千年の羽",
    "translation": "千年之羽",
    "romaji": "se n ne n no ha ne"
  },
  {
    "time": 110350,
    "lyric": "儚い祈りが",
    "translation": "渺无望之祈愿",
    "romaji": "ha ka na i i no ri ga"
  },
  {
    "time": 113460,
    "lyric": "囚われの翼",
    "translation": "乃受囚之翼",
    "romaji": "to ra wa re no tsu ba sa"
  },
  {
    "time": 116280,
    "lyric": "彷徨うより時を越えて",
    "translation": "彷徨间早已时光飞逝",
    "romaji": "ho u ko u u yo ri to ki wo ko e te"
  },
  {
    "time": 122070,
    "lyric": "虹色の羽が",
    "translation": "七色彩羽",
    "romaji": "ni ji i ro no ha ne ga"
  },
  {
    "time": 124860,
    "lyric": "釁りの道で天火を浴びよ",
    "translation": "于血染之道身负天火",
    "romaji": "ki n ri no mi chi de te n pi wo a bi yo"
  },
  {
    "time": 133660,
    "lyric": "大風に乗って",
    "translation": "身乘大风",
    "romaji": "o o ka ze ni no tte"
  },
  {
    "time": 139350,
    "lyric": "時を超えて",
    "translation": "超越时光",
    "romaji": "to ki wo ko e te"
  },
  {
    "time": 145080,
    "lyric": "大風に乗って",
    "translation": "身乘大风",
    "romaji": "o o ka ze ni no tte"
  },
  {
    "time": 147830,
    "lyric": "時を超えて",
    "translation": "超越时光",
    "romaji": "to ki wo ko e te"
  },
  {
    "time": 161260,
    "lyric": "Ah……",
    "translation": "",
    "romaji": ""
  },
  {
    "time": 167710,
    "lyric": "儚い祈りが",
    "translation": "渺无望之祈愿",
    "romaji": "ha ka na i i no ri ga"
  },
  {
    "time": 170540,
    "lyric": "囚われの翼",
    "translation": "乃受囚之翼",
    "romaji": "to ra wa re no tsu ba sa"
  },
  {
    "time": 173420,
    "lyric": "彷徨うより時を越えて",
    "translation": "彷徨间早已时光飞逝",
    "romaji": "ho u ko u u yo ri to ki wo ko e te"
  },
  {
    "time": 179330,
    "lyric": "儚い祈りを",
    "translation": "心怀渺无望之祈愿",
    "romaji": "ha ka na i i no ri wo"
  },
  {
    "time": 182070,
    "lyric": "守りの道で運命を抱いて",
    "translation": "于守护之道拥抱命运",
    "romaji": "ma mo ri no mi chi de u n me i wo da i te"
  },
  {
    "time": 182071,
    "lyric": "出品 Produced by:HOYO-MiX",
    "translation": "",
    "romaji": ""
  },
  {
    "time": 192818,
    "lyric": "混音：TSAR(HOYO-MiX)",
    "translation": "",
    "romaji": ""
  }
]